holamundofranco_dfranco92-0.0.2.dist-info/licenses/LICENSE
holamundoplayer/__init__.py
holamundoplayer/lala.py
holamundoplayer/player.py
holamundofranco_dfranco92-0.0.2.dist-info/METADATA
holamundofranco_dfranco92-0.0.2.dist-info/WHEEL
holamundofranco_dfranco92-0.0.2.dist-info/top_level.txt
holamundofranco_dfranco92-0.0.2.dist-info/RECORD
