Metadata-Version: 2.4
Name: holamundofranco_dfranco92
Version: 0.0.2
Summary: Un reproductor de ejemplo
Home-page: https://github.com/tu_usuario/holamundoplayer
Author: Daniel Franco
Author-email: micorporacion@example.com
Classifier: Programming Language :: Python :: 3
Classifier: License :: OSI Approved :: MIT License
Classifier: Operating System :: OS Independent
Requires-Python: >=3.6
License-File: LICENSE
Dynamic: author
Dynamic: author-email
Dynamic: classifier
Dynamic: description
Dynamic: description-content-type
Dynamic: home-page
Dynamic: license-file
Dynamic: requires-python
Dynamic: summary
